aiospotipy/__init__.py
aiospotipy/_http.py
aiospotipy/client.py
aiospotipy/me.py
aiospotipy/oauth2.py
aiospotipy-0.0.2.dist-info/LICENSE
aiospotipy-0.0.2.dist-info/METADATA
aiospotipy-0.0.2.dist-info/WHEEL
aiospotipy-0.0.2.dist-info/top_level.txt
aiospotipy-0.0.2.dist-info/RECORD
